Metadata-Version: 1.1
Name: cwbbus
Version: 0.0.2
Summary: Package aimed at facilitating the use of the open data from Curitiba's public transport system
Home-page: https://github.com/killertux/cwbbus
Author: Angelin01, killertux, Kabbah
Author-email: UNKNOWN
License: MIT
Download-URL: https://github.com/killertux/cwbbus/archive/0.0.2.tar.gz
Platform: UNKNOWN
